django/contrib/auth/migrations/0001_squashed_0012_alter_user_first_name_max_length.py
squashed_users-1.0.0.dist-info/LICENSE
squashed_users-1.0.0.dist-info/METADATA
squashed_users-1.0.0.dist-info/WHEEL
squashed_users-1.0.0.dist-info/top_level.txt
squashed_users-1.0.0.dist-info/RECORD
