Metadata-Version: 2.2
Name: squashed-users
Version: 1.0.0
Summary: django.contrib.auth migrations squashed into a single migration
Author-email: "Bugsink B.V." <info@bugsink.com>
License: Copyright 2025 Bugsink B.V.
Classifier: Programming Language :: Python :: 3
Requires-Python: >=3.9
License-File: LICENSE
